aklogger/__init__.py
aklogger/handlers.py
aklogger-0.2.2.dist-info/LICENSE
aklogger-0.2.2.dist-info/METADATA
aklogger-0.2.2.dist-info/WHEEL
aklogger-0.2.2.dist-info/RECORD
