Metadata-Version: 2.1
Name: aklogger
Version: 0.2.2
Summary: A generic logging package for python projects
Home-page: https://github.com/appknox/aklogger
License: MIT
Keywords: appknox,logging,aklogger
Author: Appknox
Author-email: engineering@appknox.com
Requires-Python: >=3.8,<4.0
Classifier: License :: OSI Approved :: MIT License
Classifier: Programming Language :: Python :: 3
Classifier: Programming Language :: Python :: 3.8
Classifier: Programming Language :: Python :: 3.9
Classifier: Programming Language :: Python :: 3.10
Classifier: Programming Language :: Python :: 3.11
Requires-Dist: slack-sdk (>=3.23.0,<4.0.0)
Project-URL: Repository, https://github.com/appknox/aklogger
